bearclaw/__init__.py
bearclaw/_version.py
bearclaw/feature_extraction.py
bearclaw/preprocessing.py
bearclaw/transforms.py
bearclaw/io/__init__.py
bearclaw/io/tso.py
bearclaw/io/vcf.py
bearclaw/resources/COSMIC_v3.3_CN_GRCh37.txt
bearclaw/resources/COSMIC_v3.3_DBS_GRCh37.txt
bearclaw/resources/COSMIC_v3.3_ID_GRCh37.txt
bearclaw/resources/COSMIC_v3.3_SBS_GRCh37.txt
bearclaw/resources/COSMIC_v3.4_CN_GRCh37.txt
bearclaw/resources/COSMIC_v3.4_DBS_GRCh37.txt
bearclaw/resources/COSMIC_v3.4_ID_GRCh37.txt
bearclaw/resources/COSMIC_v3.4_RNA-SBS_GRCh37.txt
bearclaw/resources/COSMIC_v3.4_SBS_GRCh37.txt
bearclaw/resources/COSMIC_v3.4_SV_GRCh38.txt
bearclaw-0.0.4.dist-info/METADATA
bearclaw-0.0.4.dist-info/WHEEL
bearclaw-0.0.4.dist-info/licenses/LICENSE
bearclaw-0.0.4.dist-info/RECORD
