Metadata-Version: 2.3
Name: bearclaw
Version: 0.0.4
Summary: Pipeline components to extract features from variants.
Project-URL: Homepage, https://gitlab.com/hylkedonker/bearclaw
Project-URL: Bug Tracker, https://gitlab.com/hylkedonker/bearclaw/-/issues
Author-email: "Hylke C. Donker" <h.c.donker@umcg.nl>
License-File: LICENSE
Classifier: License :: OSI Approved :: MIT License
Classifier: Operating System :: OS Independent
Classifier: Programming Language :: Python :: 3
Requires-Python: >=3.10
